cycompile/__init__.py
cycompile/cythonize_decorator.py
cycompile/cythonize_decorator.pyi
cycompile/py.typed
cycompile-0.1.4.dist-info/licenses/LICENSE
cycompile-0.1.4.dist-info/METADATA
cycompile-0.1.4.dist-info/WHEEL
cycompile-0.1.4.dist-info/top_level.txt
cycompile-0.1.4.dist-info/RECORD
