Metadata-Version: 2.4
Name: cycompile
Version: 0.1.4
Summary: A Python package for optimizing function performance via a Cython decorator
Home-page: https://github.com/Ranuja01/cycompile
Author: Ranuja Pinnaduwage
Author-email: Ranuja.Pinnaduwage@gmail.com
Classifier: Programming Language :: Python :: 3
Classifier: License :: OSI Approved :: Apache Software License
Classifier: Operating System :: OS Independent
Classifier: Intended Audience :: Developers
Classifier: Topic :: Scientific/Engineering
Requires-Python: >=3.8
License-File: LICENSE
Requires-Dist: Cython
Requires-Dist: setuptools
Dynamic: author
Dynamic: author-email
Dynamic: classifier
Dynamic: description
Dynamic: description-content-type
Dynamic: home-page
Dynamic: license-file
Dynamic: requires-dist
Dynamic: requires-python
Dynamic: summary
